{
  "updated_at": "2026-07-14T15:48:57.784Z",
  "profile": {
    "username": "goglobal.ai",
    "name": "Go Global AI",
    "biography": "Aplikasi Yang Bantu Kamu Yang Mau Kerja Di Luar Negri - GRATIS (basic plan)\n(Bukan Agen Tenaga Kerja)\nCerita Aku, Dia & Next Kamu ya?",
    "picture": "https://scontent-sjc6-1.cdninstagram.com/v/t51.82787-19/719425749_18113681980681178_1566073357021169758_n.jpg?stp=dst-jpg_s206x206_tt6&_nc_cat=109&ccb=7-5&_nc_sid=30ff31&efg=eyJ2ZW5jb2RlX3RhZyI6InByb2ZpbGVfcGljLnd3dy5DMyJ9&_nc_ohc=61lhNq2QdK8Q7kNvwGdTXNW&_nc_oc=Adr2jQ7rjdIGmtLVRXawdKG9GUAmb8nbGoo75tuSrDTwBv2lNn5PY2c30mM7nftZ_Kw&_nc_zt=24&_nc_ht=scontent-sjc6-1.cdninstagram.com&edm=AP4hL3IEAAAA&_nc_gid=96_kE2s1WQ-c0R5jsDDXPw&_nc_tpa=Q5bMBQF8OyFRFfLYdQGq4JJHJ5_VrrYAG8l9paBRaDgN5ZVa984QyhdvsHOrzX6JF3wKzT0m60HsbAeNBQ&oh=00_AQAt61-yM-n0HUYvN2ifYqmUXXQ8ovzT2yWVCBv4ktKrKA&oe=6A5C1B75"
  },
  "summary": {
    "followers_count": 249,
    "views": 6806,
    "likes": 159,
    "replies": 10,
    "reposts": 2,
    "quotes": 0,
    "profile_views": null,
    "engagement_total": 337,
    "engagement_rate": 2.24,
    "curiosity_score": null,
    "post_count": 25
  },
  "top_posts": [
    {
      "id": "18374016178226454",
      "text": "Dulu pernah kirim 47 lamaran kerja ke Belanda, 46 di-ghosting… 1 nyangkut. 🇳🇱\nSekarang kerja di Amsterdam, gaji 3x lip",
      "permalink": "https://www.threads.com/@goglobal.ai/post/DaxR_30GwEC",
      "timestamp": "2026-07-14T10:31:33+0000",
      "metrics": {
        "views": 4612,
        "likes": 142,
        "replies": 9,
        "reposts": 2,
        "quotes": 0,
        "shares": 6
      },
      "engagement": 153
    },
    {
      "id": "18089241272398810",
      "text": "80% crew kapal pesiar yang lolos seleksi pertama kali bukan dari jurusan pariwisata.\nModalnya? Bahasa Inggris aktif + 1 ",
      "permalink": "https://www.threads.com/@goglobal.ai/post/Daty2V4Dku_",
      "timestamp": "2026-07-13T02:01:39+0000",
      "metrics": {
        "views": 4224,
        "likes": 62,
        "replies": 27,
        "reposts": 0,
        "quotes": 0,
        "shares": 5
      },
      "engagement": 89
    },
    {
      "id": "18019862615854122",
      "text": "Ekspektasi kerja di Jepang: disiplin, gaji oke, hidup rapi.\nRealita: iya semua bener — tapi kamu juga dituntut baca suas",
      "permalink": "https://www.threads.com/@goglobal.ai/post/DatoiDkIEUE",
      "timestamp": "2026-07-13T00:31:29+0000",
      "metrics": {
        "views": 834,
        "likes": 18,
        "replies": 4,
        "reposts": 0,
        "quotes": 0,
        "shares": 0
      },
      "engagement": 22
    },
    {
      "id": "18097012034461126",
      "text": "Dimas, lulusan SMK, sekarang keliling dunia sambil digaji.\nMulai dari nol, dia join kapal pesiar dan ini yang dia dapet:",
      "permalink": "https://www.threads.com/@goglobal.ai/post/DawNVGqlmjn",
      "timestamp": "2026-07-14T00:31:34+0000",
      "metrics": {
        "views": 896,
        "likes": 14,
        "replies": 7,
        "reposts": 0,
        "quotes": 0,
        "shares": 0
      },
      "engagement": 21
    },
    {
      "id": "17864563797638875",
      "text": "Ekspektasi kerja di Australia: gaji besar, santai, langsung diterima.\nRealita Dina (27, Surabaya): 6 bulan nganggur, vis",
      "permalink": "https://www.threads.com/@goglobal.ai/post/DawXpWomjKL",
      "timestamp": "2026-07-14T02:01:39+0000",
      "metrics": {
        "views": 987,
        "likes": 10,
        "replies": 0,
        "reposts": 0,
        "quotes": 0,
        "shares": 0
      },
      "engagement": 10
    }
  ],
  "recent_posts": [
    {
      "id": "18079531043680204",
      "text": "Ada yang unik dari kerja di kapal pesiar — lo literally ganti \"negara\" setiap beberapa hari, tapi gaji tetap jalan.\nDima",
      "permalink": "https://www.threads.com/@goglobal.ai/post/DaxqDQ6oF89",
      "timestamp": "2026-07-14T14:01:43+0000",
      "metrics": {
        "views": 260,
        "likes": 2,
        "replies": 0,
        "reposts": 0,
        "quotes": 0,
        "shares": 2
      },
      "engagement": 2
    },
    {
      "id": "17890717056581565",
      "text": "Chef umur 28 yang awalnya cuma bisa masak rendang, sekarang pegang dapur di restoran Osaka.\nDia bilang hal paling susah ",
      "permalink": "https://www.threads.com/@goglobal.ai/post/DaxcUZnIEPg",
      "timestamp": "2026-07-14T12:01:43+0000",
      "metrics": {
        "views": 91,
        "likes": 2,
        "replies": 0,
        "reposts": 0,
        "quotes": 0,
        "shares": 0
      },
      "engagement": 2
    },
    {
      "id": "18374016178226454",
      "text": "Dulu pernah kirim 47 lamaran kerja ke Belanda, 46 di-ghosting… 1 nyangkut. 🇳🇱\nSekarang kerja di Amsterdam, gaji 3x lip",
      "permalink": "https://www.threads.com/@goglobal.ai/post/DaxR_30GwEC",
      "timestamp": "2026-07-14T10:31:33+0000",
      "metrics": {
        "views": 4612,
        "likes": 142,
        "replies": 9,
        "reposts": 2,
        "quotes": 0,
        "shares": 6
      },
      "engagement": 153
    },
    {
      "id": "17942072238057730",
      "text": "Orang Indo yang kerja di Kanada sering bilang hal yang sama:\ndi sana, diem itu bukan sopan — itu awkward.\nMereka belajar",
      "permalink": "https://www.threads.com/@goglobal.ai/post/DaxQPhUFf19",
      "timestamp": "2026-07-14T10:16:12+0000",
      "metrics": {
        "views": 55,
        "likes": 0,
        "replies": 0,
        "reposts": 0,
        "quotes": 0,
        "shares": 0
      },
      "engagement": 0
    },
    {
      "id": "18273441388291307",
      "text": "Honest opinion: bahasa Jerman bukan hambatan terbesar untuk kerja di sana.\nHambatan terbesarnya adalah percaya diri kamu",
      "permalink": "https://www.threads.com/@goglobal.ai/post/DaxOlHRm3Bo",
      "timestamp": "2026-07-14T10:01:40+0000",
      "metrics": {
        "views": 235,
        "likes": 7,
        "replies": 0,
        "reposts": 0,
        "quotes": 0,
        "shares": 0
      },
      "engagement": 7
    },
    {
      "id": "17956575501177646",
      "text": "Temen gue kerja di Seoul, hal pertama yang dia notice: meeting di sana mulai dan kelar tepat waktu, ga ada budaya \"benta",
      "permalink": "https://www.threads.com/@goglobal.ai/post/DawsPnxm1Fr",
      "timestamp": "2026-07-14T05:01:38+0000",
      "metrics": {
        "views": 55,
        "likes": 0,
        "replies": 0,
        "reposts": 0,
        "quotes": 0,
        "shares": 0
      },
      "engagement": 0
    },
    {
      "id": "18121747357692538",
      "text": "Remote worker itu unik — jam kerjanya \"fleksibel\" tapi somehow rapat selalu mepet subuh karena klien beda timezone.\nDulu",
      "permalink": "https://www.threads.com/@goglobal.ai/post/Dawh7ehkXY_",
      "timestamp": "2026-07-14T03:31:30+0000",
      "metrics": {
        "views": 60,
        "likes": 0,
        "replies": 0,
        "reposts": 0,
        "quotes": 0,
        "shares": 0
      },
      "engagement": 0
    },
    {
      "id": "17864563797638875",
      "text": "Ekspektasi kerja di Australia: gaji besar, santai, langsung diterima.\nRealita Dina (27, Surabaya): 6 bulan nganggur, vis",
      "permalink": "https://www.threads.com/@goglobal.ai/post/DawXpWomjKL",
      "timestamp": "2026-07-14T02:01:39+0000",
      "metrics": {
        "views": 987,
        "likes": 10,
        "replies": 0,
        "reposts": 0,
        "quotes": 0,
        "shares": 0
      },
      "engagement": 10
    },
    {
      "id": "18097012034461126",
      "text": "Dimas, lulusan SMK, sekarang keliling dunia sambil digaji.\nMulai dari nol, dia join kapal pesiar dan ini yang dia dapet:",
      "permalink": "https://www.threads.com/@goglobal.ai/post/DawNVGqlmjn",
      "timestamp": "2026-07-14T00:31:34+0000",
      "metrics": {
        "views": 896,
        "likes": 14,
        "replies": 7,
        "reposts": 0,
        "quotes": 0,
        "shares": 0
      },
      "engagement": 21
    },
    {
      "id": "18106204919025738",
      "text": "Di Eropa, CV fotonya justru sering dihapus supaya ga ada bias.\nBeda banget sama kebiasaan kita yang foto formal wajib ad",
      "permalink": "https://www.threads.com/@goglobal.ai/post/DawDCelHdQn",
      "timestamp": "2026-07-13T23:01:35+0000",
      "metrics": {
        "views": 64,
        "likes": 0,
        "replies": 0,
        "reposts": 0,
        "quotes": 0,
        "shares": 0
      },
      "engagement": 0
    }
  ]
}
