{
  "updated_at": "2026-06-21T20:02:45.869Z",
  "profile": {
    "username": "goglobal.ai",
    "name": "Go Global AI",
    "biography": "Bantu Kamu Yang Mau Kerja Di Luar Negri\n(Bukan Agent Penyalur Kerja)\n+61480746292 🇸🇭 (whatsapp)",
    "picture": "https://scontent-iad6-1.cdninstagram.com/v/t51.82787-19/719425749_18113681980681178_1566073357021169758_n.jpg?stp=dst-jpg_s206x206_tt6&_nc_cat=109&ccb=7-5&_nc_sid=30ff31&efg=eyJ2ZW5jb2RlX3RhZyI6InByb2ZpbGVfcGljLnd3dy5DMyJ9&_nc_ohc=okAGkEuj8soQ7kNvwEYmz5Z&_nc_oc=Ado-tr06t1fNve3GXyxokhJeBGki9Qi1c_ZOFMvS3qGPp_NSNZZ9JW-qIfASg49cWWU&_nc_zt=24&_nc_ht=scontent-iad6-1.cdninstagram.com&edm=AP4hL3IEAAAA&_nc_gid=THsyym5fZRXlOniGsW4wDQ&_nc_tpa=Q5bMBQFOvlQBhg7GCjvu-GGd64jMGlPe_mFdYohjJuSRHHTbvRFyn6niKgp8n1ZANlQuL-OpqB2NlvtKoA&oh=00_Af8HpNk9MB2ns8-Y_At6xnRjYSmK0iDUUtMHX0OBMteNZQ&oe=6A3E0135"
  },
  "summary": {
    "followers_count": 55,
    "views": 122,
    "likes": 1,
    "replies": 2,
    "reposts": 0,
    "quotes": 0,
    "engagement_total": 12,
    "engagement_rate": 1.88,
    "post_count": 25
  },
  "top_posts": [
    {
      "id": "17896749840472214",
      "text": "katanya kerja di Australia tanpa pengalaman itu mustahil.\neh tapi temenku yang baru lulus malah udah di Sydney sekarang ",
      "permalink": "https://www.threads.com/@goglobal.ai/post/DZyf4dOmWaa",
      "timestamp": "2026-06-20T01:20:10+0000",
      "metrics": {
        "views": 285,
        "likes": 0,
        "replies": 2,
        "reposts": 0,
        "quotes": 0,
        "shares": 0
      },
      "engagement": 2
    },
    {
      "id": "17954013150167639",
      "text": "niat kerja di kapal pesiar tapi bingung mulai dari mana? 🚢\nCV-nya harus gimana, bahasa Inggrisnya cukup nggak, agency-n",
      "permalink": "https://www.threads.com/@goglobal.ai/post/DZ09aFkjeyy",
      "timestamp": "2026-06-21T00:17:10+0000",
      "metrics": {
        "views": 3,
        "likes": 0,
        "replies": 1,
        "reposts": 0,
        "quotes": 0,
        "shares": 0
      },
      "engagement": 1
    },
    {
      "id": "18116779471874317",
      "text": "Kerja di kapal pesiar itu bukan cuma soal lucky — ada triknya 🚢\nSatu hal yang sering bikin lolos interview: cerita peng",
      "permalink": "https://www.threads.com/@goglobal.ai/post/DZ0C3nREeWa",
      "timestamp": "2026-06-20T15:45:40+0000",
      "metrics": {
        "views": 5,
        "likes": 0,
        "replies": 1,
        "reposts": 0,
        "quotes": 0,
        "shares": 0
      },
      "engagement": 1
    },
    {
      "id": "18083968256156168",
      "text": "Kerja di Jepang itu bukan cuma soal bisa bahasa Jepang, lho 🇯🇵\nBanyak perusahaan sekarang nyari orang dengan skill tek",
      "permalink": "https://www.threads.com/@goglobal.ai/post/DZz5WtSFCSa",
      "timestamp": "2026-06-20T14:22:32+0000",
      "metrics": {
        "views": 7,
        "likes": 0,
        "replies": 1,
        "reposts": 0,
        "quotes": 0,
        "shares": 0
      },
      "engagement": 1
    },
    {
      "id": "18112245460747055",
      "text": "CV kamu udah siap belum?\njadi kamu lagi galau milih Australia atau Canada?\ndua-duanya bagus, tapi buat yang belum punya ",
      "permalink": "https://www.threads.com/@goglobal.ai/post/DZzvZOuGTdZ",
      "timestamp": "2026-06-20T12:54:57+0000",
      "metrics": {
        "views": 3,
        "likes": 0,
        "replies": 1,
        "reposts": 0,
        "quotes": 0,
        "shares": 0
      },
      "engagement": 1
    }
  ],
  "recent_posts": [
    {
      "id": "18240468229309075",
      "text": "Pengen kerja di kapal pesiar tapi bingung mulai dari mana?\nBanyak yang nyerah di tahap CV sama interview karena nggak ta",
      "permalink": "https://www.threads.com/@goglobal.ai/post/DZ23Dg-lZaf",
      "timestamp": "2026-06-21T18:00:09+0000",
      "metrics": {
        "views": 1,
        "likes": 0,
        "replies": 0,
        "reposts": 0,
        "quotes": 0,
        "shares": 0
      },
      "engagement": 0
    },
    {
      "id": "18121006933706082",
      "text": "Ngirim CV ke perusahaan Jepang tapi nggak ada kabar sama sekali 😮‍💨\nBukan kamu yang salah — format CV-nya aja yang ngg",
      "permalink": "https://www.threads.com/@goglobal.ai/post/DZ2rpockd2j",
      "timestamp": "2026-06-21T16:20:30+0000",
      "metrics": {
        "views": 2,
        "likes": 0,
        "replies": 0,
        "reposts": 0,
        "quotes": 0,
        "shares": 0
      },
      "engagement": 0
    },
    {
      "id": "18077801954662928",
      "text": "Banyak yang semangat mau kerja di Eropa, tapi bingung mulai dari mana 🗺️\nVisa apa yang cocok? Gaji segitu worth it ngga",
      "permalink": "https://www.threads.com/@goglobal.ai/post/DZ2gTqelry6",
      "timestamp": "2026-06-21T14:41:22+0000",
      "metrics": {
        "views": 2,
        "likes": 0,
        "replies": 0,
        "reposts": 0,
        "quotes": 0,
        "shares": 0
      },
      "engagement": 0
    },
    {
      "id": "18053028458532700",
      "text": "Banyak yang pengen kerja di Kanada tapi bingung mulai dari mana 😮‍💨\nVisa, CV format beda, bahasa interview, semua kera",
      "permalink": "https://www.threads.com/@goglobal.ai/post/DZ2RQbCFDuN",
      "timestamp": "2026-06-21T12:29:51+0000",
      "metrics": {
        "views": 10,
        "likes": 0,
        "replies": 0,
        "reposts": 0,
        "quotes": 0,
        "shares": 0
      },
      "engagement": 0
    },
    {
      "id": "18147973108508147",
      "text": "Banyak yang mau kerja di Jerman tapi bingung mulai dari mana 😅\nVisa kerja, bahasa, pengakuan ijazah... numpuk banget ra",
      "permalink": "https://www.threads.com/@goglobal.ai/post/DZ2FC6dEU0s",
      "timestamp": "2026-06-21T10:43:09+0000",
      "metrics": {
        "views": 6,
        "likes": 0,
        "replies": 0,
        "reposts": 0,
        "quotes": 0,
        "shares": 0
      },
      "engagement": 0
    },
    {
      "id": "17991895709809052",
      "text": "Mau kerja di Korea tapi bingung mulai dari mana 😅\nVisa apa, gaji berapa, perusahaannya beneran apa enggak\nNah GoGlobal ",
      "permalink": "https://www.threads.com/@goglobal.ai/post/DZ1sCoNEfQE",
      "timestamp": "2026-06-21T07:04:40+0000",
      "metrics": {
        "views": 5,
        "likes": 0,
        "replies": 0,
        "reposts": 0,
        "quotes": 0,
        "shares": 0
      },
      "engagement": 0
    },
    {
      "id": "17882376228657366",
      "text": "Banyak yang nanya \"gimana sih caranya dapet kerja remote dari perusahaan luar?\"\nPadahal udah ngelamar sana-sini, tapi ng",
      "permalink": "https://www.threads.com/@goglobal.ai/post/DZ1rfIfFSq0",
      "timestamp": "2026-06-21T06:59:49+0000",
      "metrics": {
        "views": 6,
        "likes": 0,
        "replies": 0,
        "reposts": 0,
        "quotes": 0,
        "shares": 0
      },
      "engagement": 0
    },
    {
      "id": "17940341688057705",
      "text": "Dapet info lowongan mining di Australia dari teman teman...\nGajinya gede, benefit keren, fly-in fly-out pula.\nTapi pas m",
      "permalink": "https://www.threads.com/@goglobal.ai/post/DZ1qTPTmfcQ",
      "timestamp": "2026-06-21T06:48:55+0000",
      "metrics": {
        "views": 37,
        "likes": 0,
        "replies": 0,
        "reposts": 0,
        "quotes": 0,
        "shares": 0
      },
      "engagement": 0
    },
    {
      "id": "18475614832099006",
      "text": "Udah dapat offering dari mining company di Western Australia 🥳\nEh tapi visa-nya bingung harus mulai dari mana\nSkill Ass",
      "permalink": "https://www.threads.com/@goglobal.ai/post/DZ1qN61GWwb",
      "timestamp": "2026-06-21T06:48:12+0000",
      "metrics": {
        "views": 19,
        "likes": 0,
        "replies": 0,
        "reposts": 0,
        "quotes": 0,
        "shares": 0
      },
      "engagement": 0
    },
    {
      "id": "18061792142537713",
      "text": "niat kerja di Australia tapi bingung mulai dari mana? 🦘\nvisa, CV format bule, sampai interview pake bahasa Inggris — se",
      "permalink": "https://www.threads.com/@goglobal.ai/post/DZ1grCXDnKZ",
      "timestamp": "2026-06-21T05:25:21+0000",
      "metrics": {
        "views": 8,
        "likes": 0,
        "replies": 0,
        "reposts": 0,
        "quotes": 0,
        "shares": 0
      },
      "engagement": 0
    }
  ]
}
