{
  "updated_at": "2026-07-06T12:58:53.799Z",
  "profile": {
    "username": "goglobal.ai",
    "name": "Go Global AI",
    "biography": "Aplikasi Yang Bantu Kamu Yang Mau Kerja Di Luar Negri (GRATIS)\n(Bukan Agen Tenaga Kerja)\nCerita Aku, Dia & Next Kamu ya?",
    "picture": "https://scontent-lga3-1.cdninstagram.com/v/t51.82787-19/719425749_18113681980681178_1566073357021169758_n.jpg?stp=dst-jpg_s206x206_tt6&_nc_cat=109&ccb=7-5&_nc_sid=30ff31&efg=eyJ2ZW5jb2RlX3RhZyI6InByb2ZpbGVfcGljLnd3dy5DMyJ9&_nc_ohc=E82T2loV5VkQ7kNvwG7bjMI&_nc_oc=AdpH8pbZ-xIDToi9Uyu8WPmwu2Ohe9JwhxiwDqc0zpAdP5QATOyE-DR-H_HIUOIaixw&_nc_zt=24&_nc_ht=scontent-lga3-1.cdninstagram.com&edm=AP4hL3IEAAAA&_nc_gid=fG1r7K5-DmKBAi0dKf0ouw&_nc_tpa=Q5bMBQH7oFazU9CuJ4D2H-zKqMX5Iu9o2JGM3i6SwsWizxuyaZ3LKiulneJfteCY2bRcxWTk1r0xByA2PA&oh=00_AQAz5zJVj2vyswsv_Y7w-XZIB6Bm097hDDGIgMc9buy5Iw&oe=6A518F75"
  },
  "summary": {
    "followers_count": 187,
    "views": 831,
    "likes": 12,
    "replies": 6,
    "reposts": 0,
    "quotes": 0,
    "profile_views": null,
    "engagement_total": 69,
    "engagement_rate": 2.68,
    "curiosity_score": null,
    "post_count": 25
  },
  "top_posts": [
    {
      "id": "18636138910008136",
      "text": "Di Australia, 1 dari 3 pekerja asing kena underpayment — dibayar di bawah minimum wage yang harusnya mereka dapet.\nIni b",
      "permalink": "https://www.threads.com/@goglobal.ai/post/DabxRwnF6_k",
      "timestamp": "2026-07-06T02:01:34+0000",
      "metrics": {
        "views": 343,
        "likes": 5,
        "replies": 10,
        "reposts": 0,
        "quotes": 0,
        "shares": 0
      },
      "engagement": 15
    },
    {
      "id": "18012202394917295",
      "text": "Pernah kepikiran gak, gaji kamu bisa dateng dari tengah Samudra Mediterania?\nKerja di kapal pesiar itu bukan cuma soal t",
      "permalink": "https://www.threads.com/@goglobal.ai/post/Dabm-ajmkAt",
      "timestamp": "2026-07-06T00:31:33+0000",
      "metrics": {
        "views": 353,
        "likes": 5,
        "replies": 8,
        "reposts": 0,
        "quotes": 0,
        "shares": 0
      },
      "engagement": 13
    },
    {
      "id": "18609605608026683",
      "text": "Kerja di Korea? Bahasa Korea itu bukan bonus, hampir selalu jadi syarat.\n• Level TOPIK minimal yang diminta perusahaan l",
      "permalink": "https://www.threads.com/@goglobal.ai/post/DaXQ3szlnjk",
      "timestamp": "2026-07-04T08:01:25+0000",
      "metrics": {
        "views": 206,
        "likes": 11,
        "replies": 0,
        "reposts": 0,
        "quotes": 0,
        "shares": 0
      },
      "engagement": 11
    },
    {
      "id": "18099681841937511",
      "text": "Ekspektasi kerja di Eropa: work-life balance, 30 hari cuti, pulang jam 5 🌅\nRealita bulan pertama: masih bingung bedain ",
      "permalink": "https://www.threads.com/@goglobal.ai/post/DacoN8tIIVp",
      "timestamp": "2026-07-06T10:01:39+0000",
      "metrics": {
        "views": 185,
        "likes": 8,
        "replies": 1,
        "reposts": 0,
        "quotes": 0,
        "shares": 0
      },
      "engagement": 9
    },
    {
      "id": "17934250830092321",
      "text": "80% pekerja asing di Korea bilang skill bahasa Korea mereka cuma level \"bisa pesan makanan\" waktu pertama kali diterima ",
      "permalink": "https://www.threads.com/@goglobal.ai/post/DacF5tSltIm",
      "timestamp": "2026-07-06T05:01:47+0000",
      "metrics": {
        "views": 83,
        "likes": 1,
        "replies": 3,
        "reposts": 0,
        "quotes": 0,
        "shares": 0
      },
      "engagement": 4
    }
  ],
  "recent_posts": [
    {
      "id": "18139413505509641",
      "text": "Waktu gue pertama kerja di Jepang, gue kira senyum sambil bilang \"hai\" itu cukup buat diterima rekan kerja.\nTernyata ada",
      "permalink": "https://www.threads.com/@goglobal.ai/post/Dac18skoDt4",
      "timestamp": "2026-07-06T12:01:37+0000",
      "metrics": {
        "views": 53,
        "likes": 2,
        "replies": 1,
        "reposts": 0,
        "quotes": 0,
        "shares": 0
      },
      "engagement": 3
    },
    {
      "id": "18099681841937511",
      "text": "Ekspektasi kerja di Eropa: work-life balance, 30 hari cuti, pulang jam 5 🌅\nRealita bulan pertama: masih bingung bedain ",
      "permalink": "https://www.threads.com/@goglobal.ai/post/DacoN8tIIVp",
      "timestamp": "2026-07-06T10:01:39+0000",
      "metrics": {
        "views": 185,
        "likes": 8,
        "replies": 1,
        "reposts": 0,
        "quotes": 0,
        "shares": 0
      },
      "engagement": 9
    },
    {
      "id": "18172255399423956",
      "text": "Myth: kalau belum fasih bahasa Prancis, susah kerja di Kanada.\nReality-nya, mayoritas lowongan kerja di sini pakai bahas",
      "permalink": "https://www.threads.com/@goglobal.ai/post/DacafoRFm2-",
      "timestamp": "2026-07-06T08:01:43+0000",
      "metrics": {
        "views": 32,
        "likes": 0,
        "replies": 0,
        "reposts": 0,
        "quotes": 0,
        "shares": 0
      },
      "engagement": 0
    },
    {
      "id": "17941624833252709",
      "text": "Ekspektasi kerja di Jerman: langsung diterima karena ijazah S1.\nRealita: mereka lebih lihat portofolio + pengalaman nyat",
      "permalink": "https://www.threads.com/@goglobal.ai/post/DacQLVWkd1n",
      "timestamp": "2026-07-06T06:31:34+0000",
      "metrics": {
        "views": 326,
        "likes": 1,
        "replies": 1,
        "reposts": 0,
        "quotes": 0,
        "shares": 0
      },
      "engagement": 2
    },
    {
      "id": "17934250830092321",
      "text": "80% pekerja asing di Korea bilang skill bahasa Korea mereka cuma level \"bisa pesan makanan\" waktu pertama kali diterima ",
      "permalink": "https://www.threads.com/@goglobal.ai/post/DacF5tSltIm",
      "timestamp": "2026-07-06T05:01:47+0000",
      "metrics": {
        "views": 83,
        "likes": 1,
        "replies": 3,
        "reposts": 0,
        "quotes": 0,
        "shares": 0
      },
      "engagement": 4
    },
    {
      "id": "17873232159621500",
      "text": "Meeting jam 2 siang, tapi zona waktu mana dulu nih?\nKerja remote internasional itu seru, tapi timezone bisa bikin kepala",
      "permalink": "https://www.threads.com/@goglobal.ai/post/Dab7k0hjYbx",
      "timestamp": "2026-07-06T03:31:33+0000",
      "metrics": {
        "views": 7,
        "likes": 0,
        "replies": 0,
        "reposts": 0,
        "quotes": 0,
        "shares": 0
      },
      "engagement": 0
    },
    {
      "id": "18636138910008136",
      "text": "Di Australia, 1 dari 3 pekerja asing kena underpayment — dibayar di bawah minimum wage yang harusnya mereka dapet.\nIni b",
      "permalink": "https://www.threads.com/@goglobal.ai/post/DabxRwnF6_k",
      "timestamp": "2026-07-06T02:01:34+0000",
      "metrics": {
        "views": 343,
        "likes": 5,
        "replies": 10,
        "reposts": 0,
        "quotes": 0,
        "shares": 0
      },
      "engagement": 15
    },
    {
      "id": "18012202394917295",
      "text": "Pernah kepikiran gak, gaji kamu bisa dateng dari tengah Samudra Mediterania?\nKerja di kapal pesiar itu bukan cuma soal t",
      "permalink": "https://www.threads.com/@goglobal.ai/post/Dabm-ajmkAt",
      "timestamp": "2026-07-06T00:31:33+0000",
      "metrics": {
        "views": 353,
        "likes": 5,
        "replies": 8,
        "reposts": 0,
        "quotes": 0,
        "shares": 0
      },
      "engagement": 13
    },
    {
      "id": "18444277090142035",
      "text": "Orang Eropa itu aneh — mereka lebih percaya CV 1 halaman daripada yang panjang.\nDi Indonesia kita diajarin makin detail ",
      "permalink": "https://www.threads.com/@goglobal.ai/post/DabcsIFoPMQ",
      "timestamp": "2026-07-05T23:01:40+0000",
      "metrics": {
        "views": 33,
        "likes": 1,
        "replies": 0,
        "reposts": 0,
        "quotes": 0,
        "shares": 0
      },
      "engagement": 1
    },
    {
      "id": "18100660901154199",
      "text": "Kerja di Jepang kedengarannya keren — tapi step pertamanya bikin banyak orang stuck.\n• Visa? bingung mana yang cocok\n• G",
      "permalink": "https://www.threads.com/@goglobal.ai/post/Daae4fSFldw",
      "timestamp": "2026-07-05T14:01:35+0000",
      "metrics": {
        "views": 44,
        "likes": 0,
        "replies": 0,
        "reposts": 0,
        "quotes": 0,
        "shares": 0
      },
      "engagement": 0
    }
  ]
}
